faultylambdasensor/__init__.py
faultylambdasensor/fls.py
faultylambdasensor/fuelmap.py
faultylambdasensor/ignitionmap.py
faultylambdasensor-0.1.0.dist-info/LICENSE
faultylambdasensor-0.1.0.dist-info/METADATA
faultylambdasensor-0.1.0.dist-info/WHEEL
faultylambdasensor-0.1.0.dist-info/top_level.txt
faultylambdasensor-0.1.0.dist-info/RECORD
