Metadata-Version: 2.1
Name: faultylambdasensor
Version: 0.1.0
Summary: Get Air:Fuel Ratio, Lambda Value and Spark Angle for Any Engine
Author: Sheshank Kindalkar
Author-email: sheshankkindalkar@gmail.com
License: UNKNOWN
Project-URL: Source Code, https://github.com/SHESHANKSK/faultylambdasensor
Project-URL: BUG Tracker, https://github.com/SHESHANKSK/faultylambdasensor/issues
Keywords: python,lambdasensor,air:fule,sparkangle,automotive,fulemap,ignitionmap,faultysensor
Platform: UNKNOWN
Classifier: Development Status :: 1 - Planning
Classifier: Intended Audience :: Education
Classifier: Programming Language :: Python :: 3
Classifier: Operating System :: Unix
Classifier: Operating System :: MacOS :: MacOS X
Classifier: Operating System :: Microsoft :: Windows
License-File: LICENSE
Requires-Dist: numpy
Requires-Dist: scipy
